{
  "room": "Nas Pleblist",
  "author": "Filunovic",
  "icon": "https://cdn.discordapp.com/attachments/728370089258123265/728398564425728060/AgrE.jpg",
  "css": null,
  "rules": {
    "allowAutorespond": true,
    "allowAutowoot": true,
    "allowAutojoin": true,
    "allowAutograb": true,
    "allowSmartVote": true,
    "allowEmotes": true,
    "allowShowingMehs": true,
    "forceSmartVote": false
  },
  "ccc": {
    "admin": null,
    "ambassador": null,
    "host": null,
    "cohost": null,
    "manager": null,
    "bouncer": null,
    "rdj": "#b50ea4",
    "subscriber": null,
    "silversubscriber": null,
    "friend": null,
    "user": null
  },
  "images": {
    "background": null,
    "playback": null,
    "admin": "https://cdn.radiant.dj/rcs/icons/radiant/admin.png",
    "ambassador": "https://cdn.radiant.dj/rcs/icons/radiant/ambassador.png",
    "host": "https://cdn.discordapp.com/attachments/728370089258123265/728373662712987761/admin.png",
    "cohost": "https://cdn.discordapp.com/attachments/728370089258123265/728395406601355315/manager.png",
    "manager": "https://cdn.discordapp.com/attachments/728370089258123265/728601650536906803/mod2.jpg",
    "bouncer": "https://cdn.discordapp.com/attachments/728370089258123265/728600505349177455/mod.jpg",
    "rdj": "https://cdn.discordapp.com/attachments/728370089258123265/728600509564583977/VIP.png",
    "subscriber": null,
    "silversubscriber": "https://cdn.radiant.dj/rcs/icons/radiant/subscriber.png"
  },
  "emotes": {
    



  }
}